{"議案審議回次":"183","議案種類":"衆法","議案提出回次":"183","議案番号":"42","議案件名":"いじめ防止対策推進法案","議案提出者":"馳　浩君外十三名","衆議院予備審査議案受理年月日":"","衆議院予備付託年月日":"","衆議院予備付託委員会":"","衆議院議案受理年月日":"平成25年 6月18日","衆議院付託年月日":"平成25年 6月19日","衆議院付託委員会":"文部科学","衆議院審査終了年月日":"平成25年 6月19日","衆議院審査結果":"可決","衆議院審議終了年月日":"平成25年 6月20日","衆議院審議結果":"可決","参議院予備審査議案受理年月日":"平成25年 6月19日","参議院予備付託年月日":"平成25年 6月19日","参議院予備付託委員会":"文教科学","参議院議案受理年月日":"平成25年 6月20日","参議院付託年月日":"平成25年 6月20日","参議院付託委員会":"文教科学","参議院審査終了年月日":"平成25年 6月20日","参議院審査結果":"可決","参議院審議終了年月日":"平成25年 6月21日","参議院審議結果":"可決","公布年月日":"平成25年 6月28日","法律番号":"71"}